CHANGES.txt
TODO.txt
bootstrap.py
buildout.cfg
setup.py
src/z3c/__init__.py
src/z3c.sharedmimeinfo.egg-info/PKG-INFO
src/z3c.sharedmimeinfo.egg-info/SOURCES.txt
src/z3c.sharedmimeinfo.egg-info/dependency_links.txt
src/z3c.sharedmimeinfo.egg-info/namespace_packages.txt
src/z3c.sharedmimeinfo.egg-info/not-zip-safe
src/z3c.sharedmimeinfo.egg-info/requires.txt
src/z3c.sharedmimeinfo.egg-info/top_level.txt
src/z3c/sharedmimeinfo/README.txt
src/z3c/sharedmimeinfo/__init__.py
src/z3c/sharedmimeinfo/basedir.py
src/z3c/sharedmimeinfo/configure.zcml
src/z3c/sharedmimeinfo/interfaces.py
src/z3c/sharedmimeinfo/magic.py
src/z3c/sharedmimeinfo/mimetype.py
src/z3c/sharedmimeinfo/utility.py
src/z3c/sharedmimeinfo/tests/__init__.py
src/z3c/sharedmimeinfo/tests/test_doc.py
src/z3c/sharedmimeinfo/tests/sample_data/sample.binary
src/z3c/sharedmimeinfo/tests/sample_data/sample.doc
src/z3c/sharedmimeinfo/tests/sample_data/sample.html
src/z3c/sharedmimeinfo/tests/sample_data/sample.pdf
src/z3c/sharedmimeinfo/tests/sample_data/sample.png
src/z3c/sharedmimeinfo/tests/sample_data/sample.text