Metadata-Version: 1.0
Name: z3c.sharedmimeinfo
Version: 0.1.0
Summary: MIME type guessing framework for Zope, based on shared-mime-info
Home-page: http://pypi.python.org/pypi/z3c.sharedmimeinfo
Author: Dan Korostelev and Zope Community
Author-email: zope-dev@zope.org
License: ZPL 2.1
Platform: UNKNOWN
